jumla/__init__.py
jumla/cli.py
jumla/dataset.py
jumla/files.py
jumla/log.py
jumla/parser.py
jumla-0.1.0.dist-info/METADATA
jumla-0.1.0.dist-info/WHEEL
jumla-0.1.0.dist-info/entry_points.txt
jumla-0.1.0.dist-info/RECORD
