Metadata-Version: 2.4
Name: jumla
Version: 0.1.0
Summary: Jumla generates Lean 4 verification datasets from Python code and tests.
Author-email: Meek Msaki <meek10x@gmail.com>
Requires-Python: >=3.10
Requires-Dist: colorama>=0.4.6
